thoad/__init__.py
thoad/config.py
thoad/py.typed
thoad/differentiation/__init__.py
thoad/differentiation/engine/__init__.py
thoad/differentiation/engine/broadcasting/__init__.py
thoad/differentiation/engine/broadcasting/alignment.py
thoad/differentiation/engine/broadcasting/figuration.py
thoad/differentiation/engine/composition/__init__.py
thoad/differentiation/engine/composition/numeric/__init__.py
thoad/differentiation/engine/composition/numeric/combination.py
thoad/differentiation/engine/composition/numeric/composition.py
thoad/differentiation/engine/composition/numeric/contraction.py
thoad/differentiation/engine/composition/numeric/validation.py
thoad/differentiation/engine/composition/symbolic/__init__.py
thoad/differentiation/engine/composition/symbolic/construction.py
thoad/differentiation/engine/composition/symbolic/structure.py
thoad/differentiation/engine/control/__init__.py
thoad/differentiation/engine/control/composition.py
thoad/differentiation/engine/control/propagation.py
thoad/differentiation/engine/control/symmetry.py
thoad/differentiation/initialization/__init__.py
thoad/differentiation/initialization/assignment.py
thoad/differentiation/initialization/mapping.py
thoad/differentiation/internals/__init__.py
thoad/differentiation/internals/accumulation.py
thoad/differentiation/internals/base.py
thoad/differentiation/internals/activation/__init__.py
thoad/differentiation/internals/activation/LU/__init__.py
thoad/differentiation/internals/activation/LU/celu.py
thoad/differentiation/internals/activation/LU/elu.py
thoad/differentiation/internals/activation/LU/gelu.py
thoad/differentiation/internals/activation/LU/glu.py
thoad/differentiation/internals/activation/LU/leaky_relu.py
thoad/differentiation/internals/activation/LU/prelu.py
thoad/differentiation/internals/activation/LU/relu.py
thoad/differentiation/internals/activation/LU/rrelu.py
thoad/differentiation/internals/activation/LU/silu.py
thoad/differentiation/internals/activation/soft/__init__.py
thoad-0.1.0.dist-info/METADATA
thoad-0.1.0.dist-info/WHEEL
thoad-0.1.0.dist-info/licenses/LICENSE
thoad-0.1.0.dist-info/RECORD
