Metadata-Version: 2.4
Name: thoad
Version: 0.1.0
Summary: **thoad** (Torch High Order Automatic Differentiation) is a lightweight reverse-mode autodifferentiation engine written entirely in Python that works over PyTorch’s computational graph to compute **high order partial derivatives**. Unlike PyTorch’s native autograd - which is limited to first-order native partial derivatives - **thoad** is able to performantly propagate arbitray-order derivatives throughout the graph, enabling more advanced gradient-based computations.
Project-URL: Homepage, https://github.com/mntsx/thoad
Project-URL: Issues, https://github.com/mntsx/thoad/issues
Author-email: Miguel Montes Lorenzo <112613446+MiguelMontesLorenzo@users.noreply.github.com>
License-File: LICENSE
Requires-Python: >=3.12
Requires-Dist: torch>=2.4.1
